.gitignore
.travis.yml
CHANGES.txt
CONTRIBUTORS.txt
README.rst
bootstrap.py
buildout-cache.cfg
buildout.cfg
setup.py
travis-4.1.cfg
travis-4.2.cfg
travis-4.3.cfg
docs/LICENSE.GPL
docs/LICENSE.txt
parts/omelette/collective/multimail/MultiMailHost.py
parts/omelette/collective/multimail/ScriptableMailHost.py
parts/omelette/collective/multimail/__init__.py
parts/omelette/collective/multimail/configure.zcml
parts/omelette/collective/multimail/default_py
parts/omelette/collective/multimail/interfaces.py
parts/omelette/collective/multimail/patch.py
parts/omelette/collective/multimail/testing.py
parts/omelette/collective/multimail/testing.zcml
parts/omelette/collective/multimail/profiles/default/metadata.xml
parts/omelette/collective/multimail/profiles/default/multimailhost_various.txt
parts/omelette/collective/multimail/profiles/default/toolset.xml
parts/omelette/collective/multimail/profiles/testing/metadata.xml
parts/omelette/collective/multimail/templates/addMultiMailForm.dtml
parts/omelette/collective/multimail/templates/addScriptableMailHostForm.dtml
parts/omelette/collective/multimail/templates/setDefaultChainForm.zpt
parts/omelette/collective/multimail/tests/__init__.py
parts/omelette/collective/multimail/tests/test_easynewsletter.py
parts/omelette/collective/multimail/tests/test_multimail.py
src/collective/__init__.py
src/collective.multimail.egg-info/PKG-INFO
src/collective.multimail.egg-info/SOURCES.txt
src/collective.multimail.egg-info/dependency_links.txt
src/collective.multimail.egg-info/entry_points.txt
src/collective.multimail.egg-info/namespace_packages.txt
src/collective.multimail.egg-info/not-zip-safe
src/collective.multimail.egg-info/requires.txt
src/collective.multimail.egg-info/top_level.txt
src/collective/multimail/MultiMailHost.py
src/collective/multimail/ScriptableMailHost.py
src/collective/multimail/__init__.py
src/collective/multimail/configure.zcml
src/collective/multimail/default_py
src/collective/multimail/interfaces.py
src/collective/multimail/patch.py
src/collective/multimail/testing.py
src/collective/multimail/testing.zcml
src/collective/multimail/profiles/default/metadata.xml
src/collective/multimail/profiles/default/multimailhost_various.txt
src/collective/multimail/profiles/default/toolset.xml
src/collective/multimail/profiles/testing/metadata.xml
src/collective/multimail/templates/addMultiMailForm.dtml
