Metadata-Version: 1.1
Name: collective.multimail
Version: 1.0a6
Summary: Zope MailHost which routs mail to other MailHosts
Home-page: https://github.com/collective/collective.multimail
Author: Adam Terrey
Author-email: software@pretaweb.com
License: gpl
Platform: UNKNOWN
Classifier: Environment :: Web Environment
Classifier: Framework :: Plone
Classifier: Operating System :: OS Independent
Classifier: Programming Language :: Python
Classifier: Programming Language :: Python :: 2.6
Classifier: Topic :: Software Development :: Libraries :: Python Modules
